setup.cfg
setup.py
./chop/__init__.py
chop/__init__.py
chop/util.py
chop.egg-info/PKG-INFO
chop.egg-info/SOURCES.txt
chop.egg-info/dependency_links.txt
chop.egg-info/top_level.txt
chop/hmm/__init__.py
chop/hmm/hmm.json
chop/hmm/msr_training.utf8
chop/hmm/pku_training_words.utf8
chop/hmm/test.py
chop/hmm/train.py
chop/mmseg/__init__.py
chop/mmseg/dict.txt
chop/mmseg/punctuations.txt
chop/mmseg/test.py