Metadata-Version: 1.1
Name: chop
Version: 0.8
Summary: Chinese Words Segementation Utilities
Home-page: https://github.com/samurais/chop
Author: Hai Liang Wang
Author-email: hailiang.hl.wang@gmail.com
License: MIT
Keywords: NLP,tokenizing,Chinese word segementation
Platform: UNKNOWN
Classifier: Intended Audience :: Developers
Classifier: License :: OSI Approved :: MIT License
Classifier: Operating System :: OS Independent
Classifier: Natural Language :: Chinese (Simplified)
Classifier: Natural Language :: Chinese (Traditional)
Classifier: Programming Language :: Python
Classifier: Programming Language :: Python :: 3
Classifier: Programming Language :: Python :: 3.4
Classifier: Programming Language :: Python :: 3.5
Classifier: Programming Language :: Python :: 3.6
Classifier: Topic :: Text Processing
Classifier: Topic :: Text Processing :: Indexing
Classifier: Topic :: Text Processing :: Linguistic
